reflex_rxchat/__init__.py
reflex_rxchat/client/__init__.py
reflex_rxchat/client/rest_client.py
reflex_rxchat/client/rest_client_test.py
reflex_rxchat/client/ws_client.py
reflex_rxchat/client/ws_client_test.py
reflex_rxchat/component/__init__.py
reflex_rxchat/component/conversation.py
reflex_rxchat/component/state.py
reflex_rxchat/server/__init__.py
reflex_rxchat/server/api.py
reflex_rxchat/server/chat_server.py
reflex_rxchat/server/chat_server_test.py
reflex_rxchat/server/events.py
reflex_rxchat/server/interfaces.py
reflex_rxchat/server/models.py
reflex_rxchat/server/websocket_handler.py
reflex_rxchat/server/websocket_handler_test.py
reflex_rxchat-0.2.4.dist-info/METADATA
reflex_rxchat-0.2.4.dist-info/WHEEL
reflex_rxchat-0.2.4.dist-info/top_level.txt
reflex_rxchat-0.2.4.dist-info/RECORD
