Metadata-Version: 2.1
Name: reflex-rxchat
Version: 0.2.4
Summary: Local chat for Reflex applications
Author-email: Albert Sola <albert.sola@tardix.net>
License: Apache-2.0
Project-URL: Homepage, https://github.com/albertsola/rxchat
Keywords: reflex,reflex-custom-components
Classifier: Development Status :: 4 - Beta
Requires-Python: >=3.12
Requires-Dist: reflex>=0.6.6
Requires-Dist: aiohttp
Provides-Extra: dev
Requires-Dist: build; extra == "dev"
Requires-Dist: twine; extra == "dev"
